dfutil/__init__.py
dfutil/core.py
dfutil-0.1.1.dist-info/licenses/LICENSE
dfutil-0.1.1.dist-info/METADATA
dfutil-0.1.1.dist-info/WHEEL
dfutil-0.1.1.dist-info/top_level.txt
dfutil-0.1.1.dist-info/RECORD
