Metadata-Version: 2.4
Name: dfutil
Version: 0.1.1
Summary: A lightweight package to analyze and prepare pandas DataFrames
Author: Leon151101
License: MIT License
Keywords: pandas,dataframe
Classifier: Programming Language :: Python :: 3
Classifier: License :: OSI Approved :: MIT License
Classifier: Operating System :: OS Independent
Requires-Python: >=3.8
License-File: LICENSE
Requires-Dist: pandas>=2.0
Dynamic: license-file
